MANIFEST.in
README.txt
setup.cfg
setup.py
unice/.DS_Store
unice/__init__.py
unice.mosaique.egg-info/PKG-INFO
unice.mosaique.egg-info/SOURCES.txt
unice.mosaique.egg-info/dependency_links.txt
unice.mosaique.egg-info/entry_points.txt
unice.mosaique.egg-info/namespace_packages.txt
unice.mosaique.egg-info/not-zip-safe
unice.mosaique.egg-info/paster_plugins.txt
unice.mosaique.egg-info/requires.txt
unice.mosaique.egg-info/top_level.txt
unice/mosaique/.DS_Store
unice/mosaique/README.txt
unice/mosaique/__init__.py
unice/mosaique/config.py
unice/mosaique/configure.zcml
unice/mosaique/browser/.DS_Store
unice/mosaique/browser/__init__.py
unice/mosaique/browser/affichage_mosaique.pt
unice/mosaique/browser/affichage_mosaique.py
unice/mosaique/browser/affichage_mosaique2.pt
unice/mosaique/browser/affichage_mosaique3.pt
unice/mosaique/browser/configure.zcml
unice/mosaique/browser/macro_affichage.pt
unice/mosaique/browser/stylesheets/styles.css
unice/mosaique/content/__init__.py
unice/mosaique/content/configure.zcml
unice/mosaique/interfaces/__init__.py
unice/mosaique/portlets/__init__.py
unice/mosaique/portlets/configure.zcml
unice/mosaique/profiles/default/.DS_Store
unice/mosaique/profiles/default/cssregistry.xml
unice/mosaique/profiles/default/factorytool.xml
unice/mosaique/profiles/default/metadata.xml
unice/mosaique/profiles/default/portlets.xml
unice/mosaique/profiles/default/types.xml
unice/mosaique/profiles/default/types/.DS_Store
unice/mosaique/profiles/default/types/Folder.xml
unice/mosaique/profiles/default/types/Topic.xml
unice/mosaique/tests/__init__.py
unice/mosaique/tests/base.py
unice/mosaique/tests/test_doctest.py