Metadata-Version: 1.1
Name: unice.mosaique
Version: 1.0
Summary: Affichage des elements d'un dossier sous forme de mosaique
Home-page: http://svn.plone.org/svn/collective/
Author: Université Nice Sophia Antipolis
Author-email: pi@unice.fr
License: GPL
Platform: UNKNOWN
Classifier: Framework :: Plone
Classifier: Intended Audience :: Developers
Classifier: License :: OSI Approved :: GNU General Public License (GPL)
